[
  {
    "id": 1,
    "name": "shenleqi"
  },{
    "id": 2,
    "name": "xuhuihui"
  },{
    "id": 3,
    "name": "chensicong"
  },{
    "id": 4,
    "name": "wangjianglin"
  },{
    "id": 5,
    "name": "wangdengyu"
  },{
    "id": 6,
    "name": "yangsiyu"
  },{
    "id": 7,
    "name": "jiangyuzhou"
  },{
    "id": 8,
    "name": "liaosen"
  },{
    "id": 9,
    "name": "huxiao"
  },{
    "id": 10,
    "name": "danjie"
  },{
    "id": 11,
    "name": "gemaida"
  },{
    "id": 12,
    "name": "xiaomeiqi"
  },{
    "id": 13,
    "name": "huangyunjie"
  },{
    "id": 14,
    "name": "qijinhao"
  },{
    "id": 15,
    "name": "liuliangliang"
  },{
    "id": 16,
    "name": "xiaosifan"
  },{
    "id": 17,
    "name": "wangzuowen"
  },{
    "id": 18,
    "name": "guorunlin"
  },{
    "id": 19,
    "name": "liminghao"
  },{
    "id": 20,
    "name": "dangze"
  },{
    "id": 21,
    "name": "xiaoyizuo"
  },{
    "id": 22,
    "name": "chenxi"
  },{
    "id": 23,
    "name": "likangning"
  },{
    "id": 24,
    "name": "maqing"
  },{
    "id": 25,
    "name": "shangjie"
  },{
    "id": 26,
    "name": "yurong"
  },{
    "id": 27,
    "name": "chenzhe"
  },{
    "id": 28,
    "name": "dongxiangrui"
  },{
    "id": 29,
    "name": "chentaiyu"
  },{
    "id": 30,
    "name": "zhaoyunqi"
  },{
    "id": 31,
    "name": "zhangke"
  },{
    "id": 32,
    "name": "liaowenqiang"
  },{
    "id": 33,
    "name": "liuke"
  },{
    "id": 34,
    "name": "liaojunbin"
  },{
    "id": 35,
    "name": "lingfengyi"
  }
]